pygeoweaver/__init__.py
pygeoweaver/__main__.py
pygeoweaver/config.py
pygeoweaver/config_utils.py
pygeoweaver/constants.py
pygeoweaver/download_gw.bat
pygeoweaver/download_gw.sh
pygeoweaver/jdk_utils.py
pygeoweaver/pgw_log_config.py
pygeoweaver/pgw_spinner.py
pygeoweaver/server.py
pygeoweaver/start.sh
pygeoweaver/stop.sh
pygeoweaver/utils.py
pygeoweaver/version.py
pygeoweaver/api_call/pgw_base_api_caller.py
pygeoweaver/api_call/pgw_process_api_caller.py
pygeoweaver/api_call/pyw_workflow_api_caller.py
pygeoweaver/commands/pgw_cleanh2db.py
pygeoweaver/commands/pgw_cleanup.py
pygeoweaver/commands/pgw_create.py
pygeoweaver/commands/pgw_detail.py
pygeoweaver/commands/pgw_export.py
pygeoweaver/commands/pgw_find.py
pygeoweaver/commands/pgw_help.py
pygeoweaver/commands/pgw_history.py
pygeoweaver/commands/pgw_import.py
pygeoweaver/commands/pgw_interface.py
pygeoweaver/commands/pgw_list.py
pygeoweaver/commands/pgw_resetpassword.py
pygeoweaver/commands/pgw_run.py
pygeoweaver/commands/pgw_sync.py
pygeoweaver/commands/pgw_upgrade.py
pygeoweaver/database_management/pgw_checkpoint.py
pygeoweaver/database_management/pgw_environment.py
pygeoweaver/database_management/pgw_execution_status.py
pygeoweaver/database_management/pgw_history.py
pygeoweaver/database_management/pgw_host.py
pygeoweaver/database_management/pgw_log_activity.py
pygeoweaver/database_management/pgw_process.py
pygeoweaver/database_management/pgw_user.py
pygeoweaver/database_management/pgw_workflow.py
pygeoweaver/runtime_tags/pgw_process.py
pygeoweaver/runtime_tags/pgw_workflow.py
pygeoweaver-1.3.3.dist-info/licenses/LICENSE
pygeoweaver-1.3.3.dist-info/METADATA
pygeoweaver-1.3.3.dist-info/WHEEL
pygeoweaver-1.3.3.dist-info/entry_points.txt
pygeoweaver-1.3.3.dist-info/top_level.txt
pygeoweaver-1.3.3.dist-info/RECORD
