Metadata-Version: 2.4
Name: pygeoweaver
Version: 1.3.3
Summary: This is a wrapper package of the Geoweaver app.
Author-email: Geoweaver team <geoweaver.app@gmail.com>
Project-URL: Homepage, https://github.com/ESIPFed/pygeoweaver
Classifier: Programming Language :: Python :: 3
Classifier: License :: OSI Approved :: MIT License
Classifier: Operating System :: OS Independent
Requires-Python: <4,>=3.7
License-File: LICENSE
Requires-Dist: click
Requires-Dist: setuptools
Requires-Dist: requests
Requires-Dist: pydantic
Requires-Dist: ipython
Requires-Dist: pandas
Requires-Dist: halo
Requires-Dist: tabulate
Requires-Dist: psutil
Requires-Dist: pytest-xdist
Requires-Dist: toml
Dynamic: license-file
